django_dans_api_toolkit/__init__.py
django_dans_api_toolkit/api_response.py
django_dans_api_toolkit/api_response_handler.py
django_dans_api_toolkit/api_response_renderer.py
django_dans_api_toolkit/apps.py
django_dans_api_toolkit/py.typed
django_dans_api_toolkit/serializers/__init__.py
django_dans_api_toolkit/serializers/base.py
django_dans_api_toolkit/test/__init__.py
django_dans_api_toolkit/test/settings.py
django_dans_api_toolkit/test/test_api_response.py
django_dans_api_toolkit/test/test_api_response_handler.py
django_dans_api_toolkit/test/test_api_response_renderer.py
django_dans_api_toolkit/test/serializers/__init__.py
django_dans_api_toolkit/test/serializers/models.py
django_dans_api_toolkit/test/serializers/test_base_serializer.py
django_dans_api_toolkit-1.2.0.dist-info/AUTHORS
django_dans_api_toolkit-1.2.0.dist-info/LICENSE
django_dans_api_toolkit-1.2.0.dist-info/METADATA
django_dans_api_toolkit-1.2.0.dist-info/WHEEL
django_dans_api_toolkit-1.2.0.dist-info/top_level.txt
django_dans_api_toolkit-1.2.0.dist-info/RECORD
