Metadata-Version: 2.1
Name: django-dans-api-toolkit
Version: 1.2.0
Summary: A Django app to help make building APIs great.
Home-page: https://www.github.com/dan1229/django_dans_api_toolkit
Author: Daniel Nazarian
Author-email: dnaz@danielnazarian.com
License: BSD-3-Clause
Platform: UNKNOWN
Classifier: Environment :: Web Environment
Classifier: Framework :: Django
Classifier: Framework :: Django :: 3.1
Classifier: Framework :: Django :: 3.2
Classifier: Framework :: Django :: 4.0
Classifier: Framework :: Django :: 4.1
Classifier: Framework :: Django :: 4.2
Classifier: Framework :: Django :: 5.0
Classifier: Intended Audience :: Developers
Classifier: License :: OSI Approved :: BSD License
Classifier: Operating System :: OS Independent
Classifier: Programming Language :: Python
Classifier: Programming Language :: Python :: 3.10
Classifier: Programming Language :: Python :: 3.11
Classifier: Programming Language :: Python :: 3.12
Classifier: Topic :: Internet :: WWW/HTTP
Classifier: Topic :: Internet :: WWW/HTTP :: Dynamic Content
Requires-Python: <4.0,>=3.10
License-File: LICENSE
License-File: AUTHORS
Requires-Dist: Django>=3.1
Requires-Dist: djangorestframework>=3.14.0
